{
    "_meta": {
		"sources": [
            {
				"json": "FE",
				"abbreviation": "FE",
				"full": "Faithful of Eberron",
				"authors": [
					"Many"
				],
				"convertedBy": [
					"Tagger94"
				],
				"version": "1.0",
				"url": "",
				"targetSchema": "1.0.0"
            },
            {
				"json": "KCAA",
				"abbreviation": "KCAA",
				"full": "The Korranbern Chronicle: Adventurer's Almanac",
				"authors": [
					"Anthony J. Turco"
				],
				"convertedBy": [
					"Tagger94"
				],
				"version": "1.0",
				"url": "",
				"targetSchema": "1.0.0"
			}
		],
		"dateAdded": 1547506738545
	}
}